blog/__init__.py
blog/abstract.py
blog/locale/fr/LC_MESSAGES/django.mo
blog/locale/fr/LC_MESSAGES/django.po
blog/locale/it/LC_MESSAGES/django.mo
blog/locale/it/LC_MESSAGES/django.po
blog/locale/pt_BR/LC_MESSAGES/django.mo
blog/locale/pt_BR/LC_MESSAGES/django.po
blog/management/__init__.py
blog/management/commands/__init__.py
blog/management/commands/import_wordpress.py
blog/management/commands/wordpress_to_wagtail.py
blog/migrations/0001_initial.py
blog/migrations/0001_squashed_0006_auto_20180206_2239.py
blog/migrations/0002_auto_20150226_2305.py
blog/migrations/0002_auto_20190605_1104.py
blog/migrations/0003_auto_20150323_2116.py
blog/migrations/0003_auto_20200105_1611.py
blog/migrations/0004_auto_20150427_2047.py
blog/migrations/0005_auto_20151019_1121.py
blog/migrations/0006_auto_20180206_2239.py
blog/migrations/__init__.py
blog/models.py
blog/templates/base.html
blog/templates/blog/blog_index_page.html
blog/templates/blog/blog_page.html
blog/templates/blog/blog_post.html
blog/templates/blog/blog_post_comments_xtd.html
blog/templates/blog/blog_post_comments_xtd_link.html
blog/tests.py
blog/urls.py
blog/utils.py
blog/views.py
blog/wordpress_import.py
blog/wp_xml_parser.py
wagtail_blog-2.3.5.dist-info/LICENSE
wagtail_blog-2.3.5.dist-info/WHEEL
wagtail_blog-2.3.5.dist-info/METADATA
wagtail_blog-2.3.5.dist-info/RECORD
