Metadata-Version: 2.1
Name: wagtail-blog
Version: 2.3.5
Summary: A wordpress like blog app implemented in wagtail
Home-page: https://gitlab.com/thelabnyc/wagtail_blog
Keywords: django,wagtail,blog
Author: David Burke
Requires-Python: >=3.6,<4.0
Classifier: Development Status :: 5 - Production/Stable
Classifier: Environment :: Web Environment
Classifier: Framework :: Django
Classifier: Framework :: Wagtail
Classifier: Intended Audience :: Developers
Classifier: License :: OSI Approved :: Apache Software License
Classifier: Programming Language :: Python :: 3
Classifier: Programming Language :: Python :: 3.6
Classifier: Programming Language :: Python :: 3.7
Classifier: Programming Language :: Python :: 3.8
Requires-Dist: Django
Requires-Dist: lxml
Requires-Dist: requests
Requires-Dist: wagtail (>=2,<3)
